wfiuh/__init__.py
wfiuh/__main__.py
wfiuh/best_sample/__init__.py
wfiuh/best_sample/__main__.py
wfiuh/curve_fitting/__init__.py
wfiuh/curve_fitting/__main__.py
wfiuh/curve_fitting/fitting.py
wfiuh/curve_fitting/model.py
wfiuh/curve_fitting/models/__init__.py
wfiuh/curve_fitting/models/beta.py
wfiuh/curve_fitting/models/double_power.py
wfiuh/curve_fitting/models/double_triangular.py
wfiuh/curve_fitting/models/frechet.py
wfiuh/curve_fitting/models/gamma.py
wfiuh/curve_fitting/models/hill.py
wfiuh/curve_fitting/models/hoerl.py
wfiuh/curve_fitting/models/inverse_gaussian.py
wfiuh/curve_fitting/models/kumaraswamy.py
wfiuh/curve_fitting/models/logistic.py
wfiuh/curve_fitting/models/multistage.py
wfiuh/curve_fitting/models/normal_gaussian.py
wfiuh/curve_fitting/models/polynomial.py
wfiuh/curve_fitting/models/rational.py
wfiuh/curve_fitting/models/shiftred_log_pearson_3.py
wfiuh/curve_fitting/models/weibull.py
wfiuh/curve_fitting/utils.py
wfiuh/log/__init__.py
wfiuh/param_distribution/__init__.py
wfiuh/param_distribution/__main__.py
wfiuh-0.3.1.dist-info/METADATA
wfiuh-0.3.1.dist-info/LICENSE
wfiuh-0.3.1.dist-info/WHEEL
wfiuh-0.3.1.dist-info/RECORD
